[{"idHtmlMailTemplate":"1","code":"basic","idsAvailable":"#CONTENT","title_en":"Basic Template","titleUrl_en":"basic-template","template_en":"<table align=\"center\" border=\"0\" cellpadding=\"0\" cellspacing=\"0\" style=\"width: 600px;\"><tbody><tr><td><p style=\"text-align: center;\"><img src=\"http:\/\/localhost\/asterion\/base\/visual\/img\/logo.jpg\" \/><\/p><\/td><\/tr><tr><td>#CONTENT<\/td><\/tr><tr><td style=\"text-align: center;\"><p>Asterion - <a href=\\\"mailto:info@asterion-cms.com\\\">info@asterion-cms.com<\/a><\/p><\/td><\/tr><\/tbody><\/table>"}]